{
    "Title": "Another special guest blog post from my girlfriend Rhiannon on her research (I made the icosahedron)...",
    "Author": "Jake Koenig",
    "URL": "1229522042648576000",
    "Template": "tweet.temp",
    "Date": "02/17/2020",
    "Content": "short/1229522042648576000.md",
    "Summary": "Another special guest blog post from my girlfriend Rhiannon on her research (I made the icosahedron):",
    "Categories": [
        "tweets"
    ],
    "tweet_id": "1229522042648576000",
    "tweet_url": "https://twitter.com/ja3k_/status/1229522042648576000",
    "original_date": "Mon Feb 17 21:44:33 +0000 2020",
    "media": [],
    "quoted_tweet": null,
    "is_thread": false
}