{
    "Title": "Just noticed my microwave tray takes exactly 10 seconds to spin around. What a nice touch.",
    "Author": "Jake Koenig",
    "URL": "1284174759824109568",
    "Template": "tweet.temp",
    "Date": "07/17/2020",
    "Content": "short/1284174759824109568.md",
    "Summary": "Just noticed my microwave tray takes exactly 10 seconds to spin around. What a nice touch.",
    "Categories": [
        "tweets"
    ],
    "tweet_id": "1284174759824109568",
    "tweet_url": "https://twitter.com/ja3k_/status/1284174759824109568",
    "original_date": "Fri Jul 17 17:14:56 +0000 2020",
    "media": [],
    "quoted_tweet": null,
    "is_thread": false
}