{
    "Title": "There's nothing that annoys me more than when something I want to learn about by Googling is hidden ...",
    "Author": "Jake Koenig",
    "URL": "1361352685329543171",
    "Template": "tweet.temp",
    "Date": "02/15/2021",
    "Content": "short/1361352685329543171.md",
    "Summary": "There's nothing that annoys me more than when something I want to learn about by Googling is hidden by similar named and more popular concepts.",
    "Categories": [
        "tweets"
    ],
    "tweet_id": "1361352685329543171",
    "tweet_url": "https://twitter.com/ja3k_/status/1361352685329543171",
    "original_date": "Mon Feb 15 16:32:27 +0000 2021",
    "media": [],
    "quoted_tweet": null,
    "is_thread": false
}