{
    "Title": "It annoys me a lot that 0 comes after 9 instead of before 1 on a keyboard.",
    "Author": "Jake Koenig",
    "URL": "1367818496709697538",
    "Template": "tweet.temp",
    "Date": "03/05/2021",
    "Content": "short/1367818496709697538.md",
    "Summary": "It annoys me a lot that 0 comes after 9 instead of before 1 on a keyboard.",
    "Categories": [
        "tweets"
    ],
    "tweet_id": "1367818496709697538",
    "tweet_url": "https://twitter.com/ja3k_/status/1367818496709697538",
    "original_date": "Fri Mar 05 12:45:17 +0000 2021",
    "media": [],
    "quoted_tweet": null,
    "is_thread": false
}