{
    "Title": "Is the phrase \"ok Google\" because Larry Page is a Radiohead fan?",
    "Author": "Jake Koenig",
    "URL": "1438978569355530244",
    "Template": "tweet.temp",
    "Date": "09/17/2021",
    "Content": "short/1438978569355530244.md",
    "Summary": "Is the phrase \"ok Google\" because Larry Page is a Radiohead fan?",
    "Categories": [
        "tweets"
    ],
    "tweet_id": "1438978569355530244",
    "tweet_url": "https://twitter.com/ja3k_/status/1438978569355530244",
    "original_date": "Fri Sep 17 21:30:00 +0000 2021",
    "media": [],
    "quoted_tweet": null,
    "is_thread": false
}