{
    "Title": "I've been working on the same bag of Doritos for 3 weeks.",
    "Author": "Jake Koenig",
    "URL": "1438879517100097536",
    "Template": "tweet.temp",
    "Date": "09/17/2021",
    "Content": "short/1438879517100097536.md",
    "Summary": "I've been working on the same bag of Doritos for 3 weeks.",
    "Categories": [
        "tweets"
    ],
    "tweet_id": "1438879517100097536",
    "tweet_url": "https://twitter.com/ja3k_/status/1438879517100097536",
    "original_date": "Fri Sep 17 14:56:24 +0000 2021",
    "media": [],
    "quoted_tweet": null,
    "is_thread": false
}