{
    "Title": "I'm sorry, I can't just turn the lights off when I leave the room. Haven't you heard of Chesterton's...",
    "Author": "Jake Koenig",
    "URL": "1516019382165647367",
    "Template": "tweet.temp",
    "Date": "04/18/2022",
    "Content": "short/1516019382165647367.md",
    "Summary": "I'm sorry, I can't just turn the lights off when I leave the room. Haven't you heard of Chesterton's fence?",
    "Categories": [
        "tweets"
    ],
    "tweet_id": "1516019382165647367",
    "tweet_url": "https://twitter.com/ja3k_/status/1516019382165647367",
    "original_date": "Mon Apr 18 11:42:41 +0000 2022",
    "media": [],
    "quoted_tweet": null,
    "is_thread": false
}