{
    "Title": "Parliament read this tweet and decided it'd be easier to do the other way around.",
    "Author": "Jake Koenig",
    "URL": "1587114882964811776",
    "Template": "tweet.temp",
    "Date": "10/31/2022",
    "Content": "short/1587114882964811776.md",
    "Summary": "Parliament read this tweet and decided it'd be easier to do the other way around.",
    "Categories": [
        "tweets"
    ],
    "tweet_id": "1587114882964811776",
    "tweet_url": "https://twitter.com/ja3k_/status/1587114882964811776",
    "original_date": "Mon Oct 31 16:10:49 +0000 2022",
    "media": [],
    "quoted_tweet": null,
    "is_thread": false
}