{
    "Title": "Wait the second L isn't for Latina? Why are you all obsessed with them again?",
    "Author": "Jake Koenig",
    "URL": "1624763210418253827",
    "Template": "tweet.temp",
    "Date": "02/12/2023",
    "Content": "short/1624763210418253827.md",
    "Summary": "Wait the second L isn't for Latina? Why are you all obsessed with them again?",
    "Categories": [
        "tweets"
    ],
    "tweet_id": "1624763210418253827",
    "tweet_url": "https://twitter.com/ja3k_/status/1624763210418253827",
    "original_date": "Sun Feb 12 13:31:50 +0000 2023",
    "media": [],
    "quoted_tweet": null,
    "is_thread": false
}