{
    "Title": "week 39 of the 2.5 kids life you can really feel the pull of paternity leave",
    "Author": "Jake Koenig",
    "URL": "1628869533552480256",
    "Template": "tweet.temp",
    "Date": "02/23/2023",
    "Content": "short/1628869533552480256.md",
    "Summary": "week 39 of the 2.5 kids life you can really feel the pull of paternity leave",
    "Categories": [
        "tweets"
    ],
    "tweet_id": "1628869533552480256",
    "tweet_url": "https://twitter.com/ja3k_/status/1628869533552480256",
    "original_date": "Thu Feb 23 21:28:54 +0000 2023",
    "media": [],
    "quoted_tweet": null,
    "is_thread": false
}