{
    "Title": "In order to submit an expense to my FSA I had to run 3 unix utilities. idk how people with IQs under...",
    "Author": "Jake Koenig",
    "URL": "1650877200781160448",
    "Template": "tweet.temp",
    "Date": "04/25/2023",
    "Content": "short/1650877200781160448.md",
    "Summary": "In order to submit an expense to my FSA I had to run 3 unix utilities. idk how people with IQs under 145 navigate the world",
    "Categories": [
        "tweets"
    ],
    "tweet_id": "1650877200781160448",
    "tweet_url": "https://twitter.com/ja3k_/status/1650877200781160448",
    "original_date": "Tue Apr 25 14:59:31 +0000 2023",
    "media": [],
    "quoted_tweet": null,
    "is_thread": false
}