{
    "Title": "A plate that can't be microwaved/dishwashered might as well not be able to carry food",
    "Author": "Jake Koenig",
    "URL": "1653043152016769025",
    "Template": "tweet.temp",
    "Date": "05/01/2023",
    "Content": "short/1653043152016769025.md",
    "Summary": "A plate that can't be microwaved/dishwashered might as well not be able to carry food",
    "Categories": [
        "tweets"
    ],
    "tweet_id": "1653043152016769025",
    "tweet_url": "https://twitter.com/ja3k_/status/1653043152016769025",
    "original_date": "Mon May 01 14:26:14 +0000 2023",
    "media": [],
    "quoted_tweet": null,
    "is_thread": false
}