{
    "Title": "My daughter played with my phone for half a second and I discovered you can switch tabs on chrome by...",
    "Author": "Jake Koenig",
    "URL": "1662575117585760256",
    "Template": "tweet.temp",
    "Date": "05/27/2023",
    "Content": "short/1662575117585760256.md",
    "Summary": "My daughter played with my phone for half a second and I discovered you can switch tabs on chrome by swiping the URL bar",
    "Categories": [
        "tweets"
    ],
    "tweet_id": "1662575117585760256",
    "tweet_url": "https://twitter.com/ja3k_/status/1662575117585760256",
    "original_date": "Sat May 27 21:42:51 +0000 2023",
    "media": [],
    "quoted_tweet": null,
    "is_thread": false
}