{
    "Title": "It's funny how people just can't cope with things being great. By the numbers the macro-economy look...",
    "Author": "Jake Koenig",
    "URL": "1674784417729114118",
    "Template": "tweet.temp",
    "Date": "06/30/2023",
    "Content": "short/1674784417729114118.md",
    "Summary": "It's funny how people just can't cope with things being great. By the numbers the macro-economy looks good but everyone is forecasting a recession. Aspartame is delicious and mostly harmless but no one can believe it.",
    "Categories": [
        "tweets"
    ],
    "tweet_id": "1674784417729114118",
    "tweet_url": "https://twitter.com/ja3k_/status/1674784417729114118",
    "original_date": "Fri Jun 30 14:18:15 +0000 2023",
    "media": [],
    "quoted_tweet": null,
    "is_thread": false
}