{
    "Title": "Actually no one being able to read your tweet is a feature",
    "Author": "Jake Koenig",
    "URL": "1675592661544374272",
    "Template": "tweet.temp",
    "Date": "07/02/2023",
    "Content": "short/1675592661544374272.md",
    "Summary": "Actually no one being able to read your tweet is a feature",
    "Categories": [
        "tweets"
    ],
    "tweet_id": "1675592661544374272",
    "tweet_url": "https://twitter.com/ja3k_/status/1675592661544374272",
    "original_date": "Sun Jul 02 19:49:56 +0000 2023",
    "media": [],
    "quoted_tweet": null,
    "is_thread": false
}