{
    "Title": "Due to the ongoing writer strike this account will be posting reruns this week. We apologize for the...",
    "Author": "Jake Koenig",
    "URL": "1682557770963505152",
    "Template": "tweet.temp",
    "Date": "07/22/2023",
    "Content": "short/1682557770963505152.md",
    "Summary": "Due to the ongoing writer strike this account will be posting reruns this week. We apologize for the inconvenience and hope to be back with original content next month.",
    "Categories": [
        "tweets"
    ],
    "tweet_id": "1682557770963505152",
    "tweet_url": "https://twitter.com/ja3k_/status/1682557770963505152",
    "original_date": "Sat Jul 22 01:06:47 +0000 2023",
    "media": [],
    "quoted_tweet": null,
    "is_thread": false
}