{
    "Title": "I bet Charles Ponzi and Arpad Elo would be surprised to learn they have among the best name recognit...",
    "Author": "Jake Koenig",
    "URL": "1685060564735987712",
    "Template": "tweet.temp",
    "Date": "07/28/2023",
    "Content": "short/1685060564735987712.md",
    "Summary": "I bet Charles Ponzi and Arpad Elo would be surprised to learn they have among the best name recognition in history",
    "Categories": [
        "tweets"
    ],
    "tweet_id": "1685060564735987712",
    "tweet_url": "https://twitter.com/ja3k_/status/1685060564735987712",
    "original_date": "Fri Jul 28 22:52:00 +0000 2023",
    "media": [],
    "quoted_tweet": null,
    "is_thread": false
}