{
    "Title": "I should not have tried the sample bose headphones on at Costco. Makes me regret saving money on Mon...",
    "Author": "Jake Koenig",
    "URL": "1693644921096569321",
    "Template": "tweet.temp",
    "Date": "08/21/2023",
    "Content": "short/1693644921096569321.md",
    "Summary": "I should not have tried the sample bose headphones on at Costco. Makes me regret saving money on Monoprice. Also maybe I have lice now.",
    "Categories": [
        "tweets"
    ],
    "tweet_id": "1693644921096569321",
    "tweet_url": "https://twitter.com/ja3k_/status/1693644921096569321",
    "original_date": "Mon Aug 21 15:23:10 +0000 2023",
    "media": [],
    "quoted_tweet": null,
    "is_thread": false
}