{
    "Title": "Telling my toddler they're called trigon and quadragon",
    "Author": "Jake Koenig",
    "URL": "1714429521422946605",
    "Template": "tweet.temp",
    "Date": "10/17/2023",
    "Content": "short/1714429521422946605.md",
    "Summary": "Telling my toddler they're called trigon and quadragon",
    "Categories": [
        "tweets"
    ],
    "tweet_id": "1714429521422946605",
    "tweet_url": "https://twitter.com/ja3k_/status/1714429521422946605",
    "original_date": "Tue Oct 17 23:53:45 +0000 2023",
    "media": [],
    "quoted_tweet": null,
    "is_thread": false
}