{
    "Title": "Is anyone worried an SBF from a 0.0001% timeline where he became god emperor and time lord will cros...",
    "Author": "Jake Koenig",
    "URL": "1720751342900453880",
    "Template": "tweet.temp",
    "Date": "11/04/2023",
    "Content": "short/1720751342900453880.md",
    "Summary": "Is anyone worried an SBF from a 0.0001% timeline where he became god emperor and time lord will cross dimensions to save him?",
    "Categories": [
        "tweets"
    ],
    "tweet_id": "1720751342900453880",
    "tweet_url": "https://twitter.com/ja3k_/status/1720751342900453880",
    "original_date": "Sat Nov 04 10:34:24 +0000 2023",
    "media": [],
    "quoted_tweet": null,
    "is_thread": false
}