{
    "Title": "`colorscheme shine` was made for working outside",
    "Author": "Jake Koenig",
    "URL": "1769815492749852905",
    "Template": "tweet.temp",
    "Date": "03/18/2024",
    "Content": "short/1769815492749852905.md",
    "Summary": "`colorscheme shine` was made for working outside",
    "Categories": [
        "tweets"
    ],
    "tweet_id": "1769815492749852905",
    "tweet_url": "https://twitter.com/ja3k_/status/1769815492749852905",
    "original_date": "Mon Mar 18 19:57:49 +0000 2024",
    "media": [],
    "quoted_tweet": null,
    "is_thread": false
}