{
    "Title": "A man died two deaths. The first when he makes his first \"A man died 2 times\" riff",
    "Author": "Jake Koenig",
    "URL": "1814084204956917825",
    "Template": "tweet.temp",
    "Date": "07/18/2024",
    "Content": "short/1814084204956917825.md",
    "Summary": "A man died two deaths. The first when he makes his first \"A man died 2 times\" riff",
    "Categories": [
        "tweets"
    ],
    "tweet_id": "1814084204956917825",
    "tweet_url": "https://twitter.com/ja3k_/status/1814084204956917825",
    "original_date": "Thu Jul 18 23:45:53 +0000 2024",
    "media": [],
    "quoted_tweet": null,
    "is_thread": false
}