{
    "Title": "i've started just saying \"1.6 gallons of water\" immediately and flatly whenever someone goes to the ...",
    "Author": "Jake Koenig",
    "URL": "1841868397728113069",
    "Template": "tweet.temp",
    "Date": "10/03/2024",
    "Content": "short/1841868397728113069.md",
    "Summary": "i've started just saying \"1.6 gallons of water\" immediately and flatly whenever someone goes to the bathroom",
    "Categories": [
        "tweets"
    ],
    "tweet_id": "1841868397728113069",
    "tweet_url": "https://twitter.com/ja3k_/status/1841868397728113069",
    "original_date": "Thu Oct 03 15:50:20 +0000 2024",
    "media": [
        {
            "type": "photo",
            "url": "/asset/crosspoast/GY-hU6RbAAI8Xv7.png",
            "original_url": "http://pbs.twimg.com/media/GY-hU6RbAAI8Xv7.png"
        }
    ],
    "quoted_tweet": null,
    "is_thread": false
}