{
    "Title": "What did you get done this week?",
    "Author": "Jake Koenig",
    "URL": "1855257467254690073",
    "Template": "tweet.temp",
    "Date": "11/09/2024",
    "Content": "short/1855257467254690073.md",
    "Summary": "What did you get done this week?",
    "Categories": [
        "tweets"
    ],
    "tweet_id": "1855257467254690073",
    "tweet_url": "https://twitter.com/ja3k_/status/1855257467254690073",
    "original_date": "Sat Nov 09 14:33:43 +0000 2024",
    "media": [],
    "quoted_tweet": null,
    "is_thread": false
}