{
    "Title": "`gh pr view --web` is so much better than trying to find where the pr is already open in my tabs or ...",
    "Author": "Jake Koenig",
    "URL": "1889005999849459807",
    "Template": "tweet.temp",
    "Date": "02/10/2025",
    "Content": "short/1889005999849459807.md",
    "Summary": "`gh pr view --web` is so much better than trying to find where the pr is already open in my tabs or navigate to it from the website. The internet was a mistake.",
    "Categories": [
        "tweets"
    ],
    "tweet_id": "1889005999849459807",
    "tweet_url": "https://twitter.com/ja3k_/status/1889005999849459807",
    "original_date": "Mon Feb 10 17:38:21 +0000 2025",
    "media": [],
    "quoted_tweet": null,
    "is_thread": false
}