{
    "Title": "Jevons Paradox",
    "Author": "Jake Koenig",
    "URL": "1896613872205025563",
    "Template": "tweet.temp",
    "Date": "03/03/2025",
    "Content": "short/1896613872205025563.md",
    "Summary": "Jevons Paradox",
    "Categories": [
        "tweets"
    ],
    "tweet_id": "1896613872205025563",
    "tweet_url": "https://twitter.com/ja3k_/status/1896613872205025563",
    "original_date": "Mon Mar 03 17:29:19 +0000 2025",
    "media": [],
    "quoted_tweet": null,
    "is_thread": false
}