{
    "Title": "The thing about the greater fool theory is it turns out there's always a bigger fool",
    "Author": "Jake Koenig",
    "URL": "1896612315417784691",
    "Template": "tweet.temp",
    "Date": "03/03/2025",
    "Content": "short/1896612315417784691.md",
    "Summary": "The thing about the greater fool theory is it turns out there's always a bigger fool",
    "Categories": [
        "tweets"
    ],
    "tweet_id": "1896612315417784691",
    "tweet_url": "https://twitter.com/ja3k_/status/1896612315417784691",
    "original_date": "Mon Mar 03 17:23:08 +0000 2025",
    "media": [],
    "quoted_tweet": null,
    "is_thread": false
}