{
    "Title": "People asking how to exit vim is a classic XY program",
    "Author": "Jake Koenig",
    "URL": "1896197637344530873",
    "Template": "tweet.temp",
    "Date": "03/02/2025",
    "Content": "short/1896197637344530873.md",
    "Summary": "People asking how to exit vim is a classic XY program",
    "Categories": [
        "tweets"
    ],
    "tweet_id": "1896197637344530873",
    "tweet_url": "https://twitter.com/ja3k_/status/1896197637344530873",
    "original_date": "Sun Mar 02 13:55:21 +0000 2025",
    "media": [],
    "quoted_tweet": null,
    "is_thread": false
}