{
    "Title": "1/8th of the time gone. I feel like I started this bit yesterday",
    "Author": "Jake Koenig",
    "URL": "1913253824367902767",
    "Template": "tweet.temp",
    "Date": "04/18/2025",
    "Content": "short/1913253824367902767.md",
    "Summary": "1/8th of the time gone. I feel like I started this bit yesterday",
    "Categories": [
        "tweets"
    ],
    "tweet_id": "1913253824367902767",
    "tweet_url": "https://twitter.com/ja3k_/status/1913253824367902767",
    "original_date": "Fri Apr 18 15:30:32 +0000 2025",
    "media": [
        {
            "type": "photo",
            "url": "/asset/crosspoast/Go0-Nh7aIAANK_o.jpg",
            "original_url": "http://pbs.twimg.com/media/Go0-Nh7aIAANK_o.jpg"
        }
    ],
    "quoted_tweet": null,
    "is_thread": false
}