{
    "Title": "veo3 makes me want to use a social media site without videos. If only we still knew how to make them",
    "Author": "Jake Koenig",
    "URL": "1925152771642372272",
    "Template": "tweet.temp",
    "Date": "05/21/2025",
    "Content": "short/1925152771642372272.md",
    "Summary": "veo3 makes me want to use a social media site without videos. If only we still knew how to make them",
    "Categories": [
        "tweets"
    ],
    "tweet_id": "1925152771642372272",
    "tweet_url": "https://twitter.com/ja3k_/status/1925152771642372272",
    "original_date": "Wed May 21 11:32:43 +0000 2025",
    "media": [],
    "quoted_tweet": null,
    "is_thread": false
}