{
    "Title": "It's funny how people learn logical errors you can make, like causation vs correlation, y-axis probl...",
    "Author": "Jake Koenig",
    "URL": "1927385306770108464",
    "Template": "tweet.temp",
    "Date": "05/27/2025",
    "Content": "short/1927385306770108464.md",
    "Summary": "It's funny how people learn logical errors you can make, like causation vs correlation, y-axis problems, etc. median vs mean, and then just pattern match them without checking if they apply in the specific situation",
    "Categories": [
        "tweets"
    ],
    "tweet_id": "1927385306770108464",
    "tweet_url": "https://twitter.com/ja3k_/status/1927385306770108464",
    "original_date": "Tue May 27 15:24:00 +0000 2025",
    "media": [],
    "quoted_tweet": null,
    "is_thread": false
}