{
    "Title": "Evil breg grokman works for xai",
    "Author": "Jake Koenig",
    "URL": "1932040235514577207",
    "Template": "tweet.temp",
    "Date": "06/09/2025",
    "Content": "short/1932040235514577207.md",
    "Summary": "Evil breg grokman works for xai",
    "Categories": [
        "tweets"
    ],
    "tweet_id": "1932040235514577207",
    "tweet_url": "https://twitter.com/ja3k_/status/1932040235514577207",
    "original_date": "Mon Jun 09 11:41:02 +0000 2025",
    "media": [],
    "quoted_tweet": null,
    "is_thread": false
}