{
    "Title": "My wife walks into me in the office carefully studying this image full screen on my 32\" monitor",
    "Author": "Jake Koenig",
    "URL": "1953192489063710955",
    "Template": "tweet.temp",
    "Date": "08/06/2025",
    "Content": "short/1953192489063710955.md",
    "Summary": "My wife walks into me in the office carefully studying this image full screen on my 32\" monitor",
    "Categories": [
        "tweets"
    ],
    "tweet_id": "1953192489063710955",
    "tweet_url": "https://twitter.com/ja3k_/status/1953192489063710955",
    "original_date": "Wed Aug 06 20:32:32 +0000 2025",
    "media": [],
    "quoted_tweet": null,
    "is_thread": false
}