{
    "Title": "Costco should get into web services. Kirkland Cloud would clean up",
    "Author": "Jake Koenig",
    "URL": "1963041836022587505",
    "Template": "tweet.temp",
    "Date": "09/03/2025",
    "Content": "short/1963041836022587505.md",
    "Summary": "Costco should get into web services. Kirkland Cloud would clean up",
    "Categories": [
        "tweets"
    ],
    "tweet_id": "1963041836022587505",
    "tweet_url": "https://twitter.com/ja3k_/status/1963041836022587505",
    "original_date": "Wed Sep 03 00:50:19 +0000 2025",
    "media": [],
    "quoted_tweet": null,
    "is_thread": false
}