{
    "Title": "Thread: The fact that 7% of everyone who has lived is alive today is the most amazing th...",
    "Author": "Jake Koenig",
    "URL": "1280314976956305409",
    "Template": "tweet.temp",
    "Date": "07/07/2020",
    "Content": "short/thread_1280314976956305409.md",
    "Summary": "The fact that 7% of everyone who has lived is alive today is the most amazing thing I know. There are so many implications.\n\nIn some sense 7% of history will happen during my lifetime.\n\nI think I shou...",
    "Categories": [
        "tweets",
        "threads"
    ],
    "tweet_id": "1280314976956305409",
    "thread_urls": [
        "https://twitter.com/ja3k_/status/1280314976956305409",
        "https://twitter.com/ja3k_/status/1280314977665105932",
        "https://twitter.com/ja3k_/status/1280314978285879297",
        "https://twitter.com/ja3k_/status/1280314978952712199"
    ],
    "original_date": "Tue Jul 07 01:37:32 +0000 2020",
    "media": [],
    "is_thread": true,
    "thread_length": 4
}