{
    "Title": "Thread: I've got the rock match up down and paper is 50-50. If I can just find some tric...",
    "Author": "Jake Koenig",
    "URL": "1952141374481998259",
    "Template": "tweet.temp",
    "Date": "08/03/2025",
    "Content": "short/thread_1952141374481998259.md",
    "Summary": "I've got the rock match up down and paper is 50-50. If I can just find some tricks in the scissors matchup I'll be unstoppable\n\nThis is actually a true fact about me. I've only thrown paper since I de...",
    "Categories": [
        "tweets",
        "threads"
    ],
    "tweet_id": "1952141374481998259",
    "thread_urls": [
        "https://twitter.com/ja3k_/status/1952141374481998259",
        "https://twitter.com/ja3k_/status/1952141377233367355"
    ],
    "original_date": "Sun Aug 03 22:55:47 +0000 2025",
    "media": [],
    "is_thread": true,
    "thread_length": 2
}