{
    "Title": "Thread: Thanks to Jevon's paradox software engineering will be more highly paid every ye...",
    "Author": "Jake Koenig",
    "URL": "1542881146857369600",
    "Template": "tweet.temp",
    "Date": "07/01/2022",
    "Content": "short/thread_1542881146857369600.md",
    "Summary": "Thanks to Jevon's paradox software engineering will be more highly paid every year until they automate the last piece\n\n(and then we all get laid off (killed by nanobots) simultaneously)",
    "Categories": [
        "tweets",
        "threads"
    ],
    "tweet_id": "1542881146857369600",
    "thread_urls": [
        "https://twitter.com/ja3k_/status/1542881146857369600",
        "https://twitter.com/ja3k_/status/1598351363888795648"
    ],
    "original_date": "Fri Jul 01 14:41:45 +0000 2022",
    "media": [],
    "is_thread": true,
    "thread_length": 2
}