{
    "Title": "Thread: I remember reading a blog that said the modal (tech?) blog has three posts which...",
    "Author": "Jake Koenig",
    "URL": "1614003510143778817",
    "Template": "tweet.temp",
    "Date": "01/13/2023",
    "Content": "short/thread_1614003510143778817.md",
    "Summary": "I remember reading a blog that said the modal (tech?) blog has three posts which are: 1. talking about how they're going to blog 2. talking about how the blog is hosted 3. apologizing for not writing ...",
    "Categories": [
        "tweets",
        "threads"
    ],
    "tweet_id": "1614003510143778817",
    "thread_urls": [
        "https://twitter.com/ja3k_/status/1614003510143778817",
        "https://twitter.com/ja3k_/status/1614003514023481344"
    ],
    "original_date": "Fri Jan 13 20:56:38 +0000 2023",
    "media": [],
    "is_thread": true,
    "thread_length": 2
}