{
    "Title": "Thread: Should I go all in?",
    "Author": "Jake Koenig",
    "URL": "1953281395977294077",
    "Template": "tweet.temp",
    "Date": "08/07/2025",
    "Content": "short/thread_1953281395977294077.md",
    "Summary": "Should I go all in?\n\nI should read the rules. If they release gpt 5 without the hyphen does it resolve yes?",
    "Categories": [
        "tweets",
        "threads"
    ],
    "tweet_id": "1953281395977294077",
    "thread_urls": [
        "https://twitter.com/ja3k_/status/1953281395977294077",
        "https://twitter.com/ja3k_/status/1953283990481203366"
    ],
    "original_date": "Thu Aug 07 02:25:49 +0000 2025",
    "media": [],
    "is_thread": true,
    "thread_length": 2
}